dataframe_mapper-0.0.3.dist-info/METADATA
dataframe_mapper-0.0.3.dist-info/RECORD
dataframe_mapper-0.0.3.dist-info/WHEEL
dataframe_mapper-0.0.3.dist-info/top_level.txt
dfmapper/__init__.py
dfmapper/column.py
dfmapper/exceptions.py
dfmapper/mapper.py
dfmapper/validator.py
